qdatamatrix/__init__.py
qdatamatrix/_qcell.py
qdatamatrix/_qcelldelegate.py
qdatamatrix/_qcontextmenu.py
qdatamatrix/_qdatamatrix.py
qdatamatrix/_qspreadsheet.py
qdatamatrix/decorators.py
qdatamatrix/translate.py
qdatamatrix-0.1.34.dist-info/COPYING
qdatamatrix-0.1.34.dist-info/WHEEL
qdatamatrix-0.1.34.dist-info/METADATA
qdatamatrix-0.1.34.dist-info/RECORD
