Metadata-Version: 2.1
Name: qdatamatrix
Version: 0.1.34
Summary: This file is part of qdatamatatrix.
Keywords: data scienc3,pyqt,widget,spreadsheet
Author-email: Sebastiaan Mathôt <s.mathot@cogsci.nl>
Requires-Python: >=3.7
Requires-Dist: datamatrix
Project-URL: Documentation, https://github.com/open-cogsci/qdatamatrix
Project-URL: Source, https://github.com/open-cogsci/qdatamatrix
